slack_sdk_pydantic/__init__.py
slack_sdk_pydantic/py.typed
slack_sdk_pydantic/models/__init__.py
slack_sdk_pydantic/models/blocks.py
slack_sdk_pydantic-0.1.2.dist-info/METADATA
slack_sdk_pydantic-0.1.2.dist-info/WHEEL
slack_sdk_pydantic-0.1.2.dist-info/licenses/LICENSE
slack_sdk_pydantic-0.1.2.dist-info/RECORD
