Metadata-Version: 2.4
Name: slack_sdk_pydantic
Version: 0.1.2
Summary: Pydantic XML models for slack content to allow easily templating content
License-File: LICENSE
Requires-Python: >=3.12
Requires-Dist: lxml>=5.4.0
Requires-Dist: pydantic-xml>=2.17.0
Requires-Dist: pydantic>=2.11.4
Requires-Dist: slack-sdk>=3.35.0
